aslprep/__about__.py
aslprep/__init__.py
aslprep/__main__.py
aslprep/_version.py
aslprep/_warnings.py
aslprep/config.py
aslprep/cli/__init__.py
aslprep/cli/parser.py
aslprep/cli/run.py
aslprep/cli/version.py
aslprep/cli/workflow.py
aslprep/cli/tests/__init__.py
aslprep/cli/tests/test_parser.py
aslprep/cli/tests/test_version.py
aslprep/data/affine.json
aslprep/data/bids.json
aslprep/data/boilerplate.bib
aslprep/data/fmap-any_registration.json
aslprep/data/fmap-any_registration_testing.json
aslprep/data/fmap_atlas.nii.gz
aslprep/data/fmap_atlas_2_MNI152NLin2009cAsym_affine.mat
aslprep/data/itkIdentityTransform.txt
aslprep/data/reports-spec.yml
aslprep/data/susceptibility_syn.json
aslprep/data/translation_rigid.json
aslprep/data/atlas/HarvardOxford/HarvardOxford.bib
aslprep/data/atlas/HarvardOxford/HarvardOxfordMNI.nii.gz
aslprep/data/atlas/HarvardOxford/HarvardOxfordNodeIndex.1D
aslprep/data/atlas/HarvardOxford/HarvardOxfordNodeNames.txt
aslprep/data/atlas/schaefer200x17/schaefer200x17CommunityAffiliation.1D
aslprep/data/atlas/schaefer200x17/schaefer200x17CommunityNames.txt
aslprep/data/atlas/schaefer200x17/schaefer200x17MNI.nii.gz
aslprep/data/atlas/schaefer200x17/schaefer200x17NodeIndex.1D
aslprep/data/atlas/schaefer200x17/schaefer200x17NodeNames.txt
aslprep/data/atlas/schaefer200x17/schaefer200x17Reference.bib
aslprep/data/atlas/schaefer200x7/schaefer200x7CommunityAffiliation.1D
aslprep/data/atlas/schaefer200x7/schaefer200x7CommunityNames.txt
aslprep/data/atlas/schaefer200x7/schaefer200x7MNI.nii.gz
aslprep/data/atlas/schaefer200x7/schaefer200x7NodeIndex.1D
aslprep/data/atlas/schaefer200x7/schaefer200x7NodeNames.txt
aslprep/data/atlas/schaefer200x7/schaefer200x7Reference.bib
aslprep/data/atlas/schaefer400x17/schaefer400x17CommunityAffiliation.1D
aslprep/data/atlas/schaefer400x17/schaefer400x17CommunityNames.txt
aslprep/data/atlas/schaefer400x17/schaefer400x17MNI.nii.gz
aslprep/data/atlas/schaefer400x17/schaefer400x17NodeIndex.1D
aslprep-0.2.7.dist-info/LICENSE
aslprep-0.2.7.dist-info/METADATA
aslprep-0.2.7.dist-info/WHEEL
aslprep-0.2.7.dist-info/entry_points.txt
aslprep-0.2.7.dist-info/top_level.txt
aslprep-0.2.7.dist-info/RECORD
