Metadata-Version: 2.1
Name: aslprep
Version: 0.2.7
Summary: ASLPREP is a robust and easy-to-use pipeline for preprocessing of diverse ASL data.
Home-page: https://github.com/pennlinc/aslprep
Author: Azeez Adebimpe
Author-email: azeez.adebimpe@outlook.com
License: 3-clause BSD
Project-URL: Documentation, https://aslprep.readthedocs.io/
Project-URL: Docker Images, https://hub.docker.com/r/pennlinc/aslprep/tags/
Platform: UNKNOWN
Classifier: Development Status :: 4 - Beta
Classifier: Intended Audience :: Science/Research
Classifier: Topic :: Scientific/Engineering :: Image Recognition
Classifier: License :: OSI Approved :: BSD License
Classifier: Programming Language :: Python :: 3.7
Classifier: Programming Language :: Python :: 3.8
Requires-Python: >=3.7
Requires-Dist: indexed-gzip (>=0.8.8)
Requires-Dist: nibabel (>=3.0)
Requires-Dist: nipype (>=1.4)
Requires-Dist: nitime
Requires-Dist: nitransforms (<20.2,>=20.0.0rc3)
Requires-Dist: numpy (>=1.16.5)
Requires-Dist: sentry-sdk (>=0.6.9)
Requires-Dist: pandas
Requires-Dist: psutil (>=5.4)
Requires-Dist: pybids (~=0.11.0)
Requires-Dist: pyyaml
Requires-Dist: sdcflows (~=1.3.1)
Requires-Dist: svgutils (==0.3.1)
Requires-Dist: tedana (<0.0.10,>=0.0.9a1)
Requires-Dist: templateflow (==0.6.3)
Requires-Dist: toml
Provides-Extra: all
Requires-Dist: datalad ; extra == 'all'
Requires-Dist: nbsphinx ; extra == 'all'
Requires-Dist: packaging ; extra == 'all'
Requires-Dist: pydot (>=1.2.3) ; extra == 'all'
Requires-Dist: pydotplus ; extra == 'all'
Requires-Dist: sphinx (<3,>=1.5.3) ; extra == 'all'
Requires-Dist: sphinx-argparse ; extra == 'all'
Requires-Dist: sphinx-rtd-theme ; extra == 'all'
Requires-Dist: sphinxcontrib-napoleon ; extra == 'all'
Requires-Dist: duecredit ; extra == 'all'
Requires-Dist: sentry-sdk (>=0.6.9) ; extra == 'all'
Requires-Dist: coverage ; extra == 'all'
Requires-Dist: codecov ; extra == 'all'
Requires-Dist: pytest ; extra == 'all'
Provides-Extra: datalad
Requires-Dist: datalad ; extra == 'datalad'
Provides-Extra: doc
Requires-Dist: nbsphinx ; extra == 'doc'
Requires-Dist: packaging ; extra == 'doc'
Requires-Dist: pydot (>=1.2.3) ; extra == 'doc'
Requires-Dist: pydotplus ; extra == 'doc'
Requires-Dist: sphinx (<3,>=1.5.3) ; extra == 'doc'
Requires-Dist: sphinx-argparse ; extra == 'doc'
Requires-Dist: sphinx-rtd-theme ; extra == 'doc'
Requires-Dist: sphinxcontrib-napoleon ; extra == 'doc'
Provides-Extra: docs
Requires-Dist: nbsphinx ; extra == 'docs'
Requires-Dist: packaging ; extra == 'docs'
Requires-Dist: pydot (>=1.2.3) ; extra == 'docs'
Requires-Dist: pydotplus ; extra == 'docs'
Requires-Dist: sphinx (<3,>=1.5.3) ; extra == 'docs'
Requires-Dist: sphinx-argparse ; extra == 'docs'
Requires-Dist: sphinx-rtd-theme ; extra == 'docs'
Requires-Dist: sphinxcontrib-napoleon ; extra == 'docs'
Provides-Extra: duecredit
Requires-Dist: duecredit ; extra == 'duecredit'
Provides-Extra: resmon
Provides-Extra: sentry
Requires-Dist: sentry-sdk (>=0.6.9) ; extra == 'sentry'
Provides-Extra: tests
Requires-Dist: coverage ; extra == 'tests'
Requires-Dist: codecov ; extra == 'tests'
Requires-Dist: pytest ; extra == 'tests'
